python_toolbox/__init__.py
python_toolbox/abc_tools.py
python_toolbox/change_tracker.py
python_toolbox/color_tools.py
python_toolbox/comparison_tools.py
python_toolbox/copy_mode.py
python_toolbox/copy_tools.py
python_toolbox/cute_enum.py
python_toolbox/cute_iter_tools.py
python_toolbox/cute_testing.py
python_toolbox/decorator_tools.py
python_toolbox/dict_tools.py
python_toolbox/exceptions.py
python_toolbox/file_tools.py
python_toolbox/function_anchoring_type.py
python_toolbox/future_tools.py
python_toolbox/gc_tools.py
python_toolbox/import_tools.py
python_toolbox/introspection_tools.py
python_toolbox/logic_tools.py
python_toolbox/monkeypatch_copyreg.py
python_toolbox/monkeypatch_envelopes.py
python_toolbox/monkeypatching_tools.py
python_toolbox/number_encoding.py
python_toolbox/os_tools.py
python_toolbox/path_tools.py
python_toolbox/pickle_tools.py
python_toolbox/poshing.py
python_toolbox/process_priority.py
python_toolbox/queue_tools.py
python_toolbox/random_tools.py
python_toolbox/re_tools.py
python_toolbox/reasoned_bool.py
python_toolbox/rst_tools.py
python_toolbox/segment_tools.py
python_toolbox/string_cataloging.py
python_toolbox/sys_tools.py
python_toolbox/temp_file_tools.py
python_toolbox/version_info.py
python_toolbox/zip_tools.py
python_toolbox/address_tools/__init__.py
python_toolbox/address_tools/object_to_string.py
python_toolbox/address_tools/shared.py
python_toolbox/address_tools/string_to_object.py
python_toolbox/binary_search/__init__.py
python_toolbox/binary_search/binary_search_profile.py
python_toolbox/binary_search/functions.py
python_toolbox/binary_search/roundings.py
python_toolbox/caching/__init__.py
python_toolbox/caching/cached_property.py
python_toolbox/caching/cached_type.py
python_toolbox/caching/decorators.py
python_toolbox/cheat_hashing/__init__.py
python_toolbox/cheat_hashing/cheat_hash.py
python_toolbox/cheat_hashing/cheat_hash_functions.py
python_toolbox/combi/__init__.py
python_toolbox/combi/chain_space.py
python_toolbox-1.3.0.dist-info/licenses/LICENSE
python_toolbox-1.3.0.dist-info/METADATA
python_toolbox-1.3.0.dist-info/WHEEL
python_toolbox-1.3.0.dist-info/entry_points.txt
python_toolbox-1.3.0.dist-info/top_level.txt
python_toolbox-1.3.0.dist-info/RECORD
